HISTORY.txt
README.txt
setup.cfg
setup.py
src/ClueMapperChatter.egg-info/PKG-INFO
src/ClueMapperChatter.egg-info/SOURCES.txt
src/ClueMapperChatter.egg-info/dependency_links.txt
src/ClueMapperChatter.egg-info/entry_points.txt
src/ClueMapperChatter.egg-info/namespace_packages.txt
src/ClueMapperChatter.egg-info/not-zip-safe
src/ClueMapperChatter.egg-info/requires.txt
src/ClueMapperChatter.egg-info/top_level.txt
src/clue/__init__.py
src/clue/chatter/__init__.py
src/clue/chatter/svnnotify.py