Metadata-Version: 1.0
Name: ClueMapperChatter
Version: 0.6
Summary: Instant messaging plugin for ClueMapper.
Home-page: http://www.cluemapper.org
Author: Rocky Burt
Author-email: rocky@serverzen.com
License: BSD
Keywords: irc im
Platform: UNKNOWN
Classifier: Programming Language :: Python
Classifier: Topic :: Software Development :: Libraries :: Python Modules
